contextooor/.env.example
contextooor/.gitignore
contextooor/__init__.py
contextooor/btc.py
contextooor/eth.py
contextooor/eth_uniswap.py
contextooor/etherscan_testing.py
contextooor/near.py
contextooor/ofac_btc_cronjob.py
contextooor/sol.py
contextooor/core/safe_math.py
contextooor/core/Chainalysis/chainalysis_ofac_api.py
contextooor/core/V2_router/V2_router.py
contextooor/core/V3_router/V3_router.py
contextooor/core/universal_router/V2_universal_router.py
contextooor/core/universal_router/V3_universal_router.py
contextooor/core/universal_router/data.py
contextooor/core/universal_router/policies.py
contextooor-0.9.9.92.dist-info/WHEEL
contextooor-0.9.9.92.dist-info/METADATA
contextooor-0.9.9.92.dist-info/RECORD
