Metadata-Version: 2.1
Name: contextooor
Version: 0.9.9.92
Summary: "Get contextual information before broadcasting a transaction."
Author-email: David Desjardins <david.thegardens@gmail.com>
Requires-Dist: web3>=6.11.4
Requires-Dist: uniswap_universal_router_decoder
Requires-Dist: python_bitcoinlib
Requires-Dist: polars
Requires-Dist: slither-analyzer
Requires-Dist: slitherin
Requires-Dist: solc-select
Requires-Dist: pytest
